{
  "config": {
    "initial_capital": 30.0,
    "leverage": 1000000.0,
    "symbol": "GBPUSD",
    "risk_per_trade_pct": 20.0,
    "spread_pips": 1.5
  },
  "summary": {
    "total_trades": 100,
    "winning_trades": 87,
    "losing_trades": 13,
    "win_rate": 87.0,
    "net_profit": 124.6,
    "profit_factor": 1.37,
    "max_drawdown_pct": 77.54,
    "sharpe_ratio": 11.29,
    "expectancy": 1.25,
    "avg_r_multiple": 0.24
  },
  "by_hour": {
    "win_rate": {
      "20": 100.0,
      "19": 100.0,
      "21": 100.0,
      "3": 80.0,
      "4": 100.0,
      "6": 100.0,
      "7": 100.0,
      "22": 100.0,
      "2": 16.67,
      "9": 100.0,
      "18": 100.0,
      "11": 100.0,
      "12": 100.0,
      "15": 100.0,
      "0": 100.0,
      "5": 100.0,
      "8": 100.0,
      "13": 100.0,
      "1": 50.0
    },
    "pnl": {
      "20": 5.5,
      "19": 2.0,
      "21": 5.63,
      "3": -22.16,
      "4": 12.13,
      "6": 5.75,
      "7": 2.7,
      "22": 15.0,
      "2": -265.26,
      "9": 7.9,
      "18": 9.0,
      "11": 3.05,
      "12": 67.35,
      "15": 1.7,
      "0": 1.0,
      "5": 37.7,
      "8": 24.8,
      "13": 180.0,
      "1": 30.82
    }
  },
  "by_day": {
    "win_rate": {
      "Monday": 68.29268292682927,
      "Tuesday": 100.0,
      "Wednesday": 100.0,
      "Thursday": 100.0,
      "Friday": 100.0,
      "Saturday": 0,
      "Sunday": 0
    },
    "pnl": {
      "Monday": -235.48,
      "Tuesday": 34.35,
      "Wednesday": 8.1,
      "Thursday": 75.13,
      "Friday": 242.5,
      "Saturday": 0.0,
      "Sunday": 0.0
    }
  },
  "trades": [
    {
      "id": 7,
      "direction": "SELL",
      "entry_time": "2026-01-05 20:50:00",
      "entry_price": 1.3544987727532285,
      "exit_time": "2026-01-05 23:55:00",
      "exit_price": 1.3533987727532284,
      "exit_reason": "TP_HIT",
      "pnl_pips": 11.000000000001009,
      "pnl_dollars": 1.100000000000101,
      "lots": 0.01,
      "r_multiple": 0.275000000000025,
      "duration_minutes": 185,
      "signal_source": "REVERSION_SNIPER",
      "confidence": 99.0
    },
    {
      "id": 8,
      "direction": "SELL",
      "entry_time": "2026-01-05 20:50:00",
      "entry_price": 1.3544934836587794,
      "exit_time": "2026-01-05 23:55:00",
      "exit_price": 1.3533934836587793,
      "exit_reason": "TP_HIT",
      "pnl_pips": 11.000000000001009,
      "pnl_dollars": 1.100000000000101,
      "lots": 0.01,
      "r_multiple": 0.275000000000025,
      "duration_minutes": 185,
      "signal_source": "REVERSION_SNIPER",
      "confidence": 99.0
    },
    {
      "id": 9,
      "direction": "SELL",
      "entry_time": "2026-01-05 20:50:00",
      "entry_price": 1.354477527667095,
      "exit_time": "2026-01-05 23:55:00",
      "exit_price": 1.353377527667095,
      "exit_reason": "TP_HIT",
      "pnl_pips": 11.000000000001009,
      "pnl_dollars": 1.100000000000101,
      "lots": 0.01,
      "r_multiple": 0.275000000000025,
      "duration_minutes": 185,
      "signal_source": "REVERSION_SNIPER",
      "confidence": 99.0
    },
    {
      "id": 10,
      "direction": "SELL",
      "entry_time": "2026-01-05 20:50:00",
      "entry_price": 1.3544584979854621,
      "exit_time": "2026-01-05 23:55:00",
      "exit_price": 1.353358497985462,
      "exit_reason": "TP_HIT",
      "pnl_pips": 11.000000000001009,
      "pnl_dollars": 1.100000000000101,
      "lots": 0.01,
      "r_multiple": 0.275000000000025,
      "duration_minutes": 185,
      "signal_source": "REVERSION_SNIPER",
      "confidence": 99.0
    },
    {
      "id": 11,
      "direction": "SELL",
      "entry_time": "2026-01-05 20:50:00",
      "entry_price": 1.3544754277312046,
      "exit_time": "2026-01-05 23:55:00",
      "exit_price": 1.3533754277312045,
      "exit_reason": "TP_HIT",
      "pnl_pips": 11.000000000001009,
      "pnl_dollars": 1.100000000000101,
      "lots": 0.01,
      "r_multiple": 0.275000000000025,
      "duration_minutes": 185,
      "signal_source": "REVERSION_SNIPER",
      "confidence": 99.0
    },
    {
      "id": 5,
      "direction": "SELL",
      "entry_time": "2026-01-05 19:20:00",
      "entry_price": 1.35414253664281,
      "exit_time": "2026-01-06 00:30:00",
      "exit_price": 1.3531425366428098,
      "exit_reason": "TP_HIT",
      "pnl_pips": 10.000000000001119,
      "pnl_dollars": 1.000000000000112,
      "lots": 0.01,
      "r_multiple": 0.25000000000002776,
      "duration_minutes": 310,
      "signal_source": "MOMENTUM_BREAKOUT",
      "confidence": 99.0
    },
    {
      "id": 6,
      "direction": "SELL",
      "entry_time": "2026-01-05 19:20:00",
      "entry_price": 1.3541421776724771,
      "exit_time": "2026-01-06 00:30:00",
      "exit_price": 1.3531421776724772,
      "exit_reason": "TP_HIT",
      "pnl_pips": 9.999999999998899,
      "pnl_dollars": 0.9999999999998899,
      "lots": 0.01,
      "r_multiple": 0.24999999999997224,
      "duration_minutes": 310,
      "signal_source": "MOMENTUM_BREAKOUT",
      "confidence": 99.0
    },
    {
      "id": 12,
      "direction": "SELL",
      "entry_time": "2026-01-05 21:35:00",
      "entry_price": 1.3541652908936626,
      "exit_time": "2026-01-06 00:35:00",
      "exit_price": 1.3530402908936625,
      "exit_reason": "TP_HIT",
      "pnl_pips": 11.250000000000426,
      "pnl_dollars": 1.1250000000000426,
      "lots": 0.01,
      "r_multiple": 0.2812500000000104,
      "duration_minutes": 180,
      "signal_source": "REVERSION_SNIPER",
      "confidence": 99.0
    },
    {
      "id": 13,
      "direction": "SELL",
      "entry_time": "2026-01-05 21:35:00",
      "entry_price": 1.3541418603828075,
      "exit_time": "2026-01-06 00:35:00",
      "exit_price": 1.3530168603828074,
      "exit_reason": "TP_HIT",
      "pnl_pips": 11.250000000000426,
      "pnl_dollars": 1.1250000000000426,
      "lots": 0.01,
      "r_multiple": 0.2812500000000104,
      "duration_minutes": 180,
      "signal_source": "REVERSION_SNIPER",
      "confidence": 99.0
    },
    {
      "id": 14,
      "direction": "SELL",
      "entry_time": "2026-01-05 21:35:00",
      "entry_price": 1.3541305984006569,
      "exit_time": "2026-01-06 00:35:00",
      "exit_price": 1.3530055984006568,
      "exit_reason": "TP_HIT",
      "pnl_pips": 11.250000000000426,
      "pnl_dollars": 1.1250000000000426,
      "lots": 0.01,
      "r_multiple": 0.2812500000000104,
      "duration_minutes": 180,
      "signal_source": "REVERSION_SNIPER",
      "confidence": 99.0
    },
    {
      "id": 15,
      "direction": "SELL",
      "entry_time": "2026-01-05 21:35:00",
      "entry_price": 1.3541514286366159,
      "exit_time": "2026-01-06 00:35:00",
      "exit_price": 1.3530264286366158,
      "exit_reason": "TP_HIT",
      "pnl_pips": 11.250000000000426,
      "pnl_dollars": 1.1250000000000426,
      "lots": 0.01,
      "r_multiple": 0.2812500000000104,
      "duration_minutes": 180,
      "signal_source": "REVERSION_SNIPER",
      "confidence": 99.0
    },
    {
      "id": 16,
      "direction": "SELL",
      "entry_time": "2026-01-05 21:35:00",
      "entry_price": 1.3541646593057846,
      "exit_time": "2026-01-06 00:35:00",
      "exit_price": 1.3530396593057845,
      "exit_reason": "TP_HIT",
      "pnl_pips": 11.250000000000426,
      "pnl_dollars": 1.1250000000000426,
      "lots": 0.01,
      "r_multiple": 0.2812500000000104,
      "duration_minutes": 180,
      "signal_source": "REVERSION_SNIPER",
      "confidence": 99.0
    },
    {
      "id": 31,
      "direction": "SELL",
      "entry_time": "2026-01-06 03:35:00",
      "entry_price": 1.3559465047692065,
      "exit_time": "2026-01-06 09:10:00",
      "exit_price": 1.3549465047692064,
      "exit_reason": "TP_HIT",
      "pnl_pips": 10.000000000001119,
      "pnl_dollars": 1.000000000000112,
      "lots": 0.01,
      "r_multiple": 0.25000000000002776,
      "duration_minutes": 335,
      "signal_source": "MOMENTUM_BREAKOUT",
      "confidence": 99.0
    },
    {
      "id": 32,
      "direction": "SELL",
      "entry_time": "2026-01-06 03:35:00",
      "entry_price": 1.3559432094922264,
      "exit_time": "2026-01-06 09:10:00",
      "exit_price": 1.3549432094922262,
      "exit_reason": "TP_HIT",
      "pnl_pips": 10.000000000001119,
      "pnl_dollars": 1.000000000000112,
      "lots": 0.01,
      "r_multiple": 0.25000000000002776,
      "duration_minutes": 335,
      "signal_source": "MOMENTUM_BREAKOUT",
      "confidence": 99.0
    },
    {
      "id": 33,
      "direction": "SELL",
      "entry_time": "2026-01-06 04:35:00",
      "entry_price": 1.3556998344287976,
      "exit_time": "2026-01-06 09:20:00",
      "exit_price": 1.3546998344287977,
      "exit_reason": "TP_HIT",
      "pnl_pips": 9.999999999998899,
      "pnl_dollars": 0.9999999999998899,
      "lots": 0.01,
      "r_multiple": 0.24999999999997224,
      "duration_minutes": 285,
      "signal_source": "MOMENTUM_BREAKOUT",
      "confidence": 99.0
    },
    {
      "id": 34,
      "direction": "SELL",
      "entry_time": "2026-01-06 04:35:00",
      "entry_price": 1.3557114901102458,
      "exit_time": "2026-01-06 09:20:00",
      "exit_price": 1.3547114901102457,
      "exit_reason": "TP_HIT",
      "pnl_pips": 10.000000000001119,
      "pnl_dollars": 1.000000000000112,
      "lots": 0.01,
      "r_multiple": 0.25000000000002776,
      "duration_minutes": 285,
      "signal_source": "MOMENTUM_BREAKOUT",
      "confidence": 99.0
    },
    {
      "id": 29,
      "direction": "SELL",
      "entry_time": "2026-01-06 03:10:00",
      "entry_price": 1.3552509637956391,
      "exit_time": "2026-01-06 09:30:00",
      "exit_price": 1.3542509637956393,
      "exit_reason": "TP_HIT",
      "pnl_pips": 9.999999999998899,
      "pnl_dollars": 0.9999999999998899,
      "lots": 0.01,
      "r_multiple": 0.24999999999997224,
      "duration_minutes": 380,
      "signal_source": "MOMENTUM_BREAKOUT",
      "confidence": 99.0
    },
    {
      "id": 30,
      "direction": "SELL",
      "entry_time": "2026-01-06 03:10:00",
      "entry_price": 1.3552418528845542,
      "exit_time": "2026-01-06 09:30:00",
      "exit_price": 1.3542418528845541,
      "exit_reason": "TP_HIT",
      "pnl_pips": 10.000000000001119,
      "pnl_dollars": 1.000000000000112,
      "lots": 0.01,
      "r_multiple": 0.25000000000002776,
      "duration_minutes": 380,
      "signal_source": "MOMENTUM_BREAKOUT",
      "confidence": 99.0
    },
    {
      "id": 35,
      "direction": "SELL",
      "entry_time": "2026-01-06 06:35:00",
      "entry_price": 1.355534191485682,
      "exit_time": "2026-01-06 09:30:00",
      "exit_price": 1.354384191485682,
      "exit_reason": "TP_HIT",
      "pnl_pips": 11.499999999999844,
      "pnl_dollars": 1.1499999999999844,
      "lots": 0.01,
      "r_multiple": 0.2874999999999958,
      "duration_minutes": 175,
      "signal_source": "REVERSION_SNIPER",
      "confidence": 99.0
    },
    {
      "id": 36,
      "direction": "SELL",
      "entry_time": "2026-01-06 06:35:00",
      "entry_price": 1.3555098173710194,
      "exit_time": "2026-01-06 09:30:00",
      "exit_price": 1.3543598173710194,
      "exit_reason": "TP_HIT",
      "pnl_pips": 11.499999999999844,
      "pnl_dollars": 1.1499999999999844,
      "lots": 0.01,
      "r_multiple": 0.2874999999999958,
      "duration_minutes": 175,
      "signal_source": "REVERSION_SNIPER",
      "confidence": 99.0
    },
    {
      "id": 37,
      "direction": "SELL",
      "entry_time": "2026-01-06 06:35:00",
      "entry_price": 1.3555085137533136,
      "exit_time": "2026-01-06 09:30:00",
      "exit_price": 1.3543585137533136,
      "exit_reason": "TP_HIT",
      "pnl_pips": 11.499999999999844,
      "pnl_dollars": 1.1499999999999844,
      "lots": 0.01,
      "r_multiple": 0.2874999999999958,
      "duration_minutes": 175,
      "signal_source": "REVERSION_SNIPER",
      "confidence": 99.0
    },
    {
      "id": 38,
      "direction": "SELL",
      "entry_time": "2026-01-06 06:35:00",
      "entry_price": 1.3555421706841866,
      "exit_time": "2026-01-06 09:30:00",
      "exit_price": 1.3543921706841866,
      "exit_reason": "TP_HIT",
      "pnl_pips": 11.499999999999844,
      "pnl_dollars": 1.1499999999999844,
      "lots": 0.01,
      "r_multiple": 0.2874999999999958,
      "duration_minutes": 175,
      "signal_source": "REVERSION_SNIPER",
      "confidence": 99.0
    },
    {
      "id": 39,
      "direction": "SELL",
      "entry_time": "2026-01-06 06:35:00",
      "entry_price": 1.3555376354867261,
      "exit_time": "2026-01-06 09:30:00",
      "exit_price": 1.3543876354867261,
      "exit_reason": "TP_HIT",
      "pnl_pips": 11.499999999999844,
      "pnl_dollars": 1.1499999999999844,
      "lots": 0.01,
      "r_multiple": 0.2874999999999958,
      "duration_minutes": 175,
      "signal_source": "REVERSION_SNIPER",
      "confidence": 99.0
    },
    {
      "id": 40,
      "direction": "SELL",
      "entry_time": "2026-01-06 07:40:00",
      "entry_price": 1.355320475796208,
      "exit_time": "2026-01-06 09:55:00",
      "exit_price": 1.353970475796208,
      "exit_reason": "TP_HIT",
      "pnl_pips": 13.499999999999623,
      "pnl_dollars": 1.3499999999999623,
      "lots": 0.01,
      "r_multiple": 0.3374999999999903,
      "duration_minutes": 135,
      "signal_source": "MOMENTUM_BREAKOUT",
      "confidence": 99.0
    },
    {
      "id": 41,
      "direction": "SELL",
      "entry_time": "2026-01-06 07:40:00",
      "entry_price": 1.3553174704168727,
      "exit_time": "2026-01-06 09:55:00",
      "exit_price": 1.3539674704168727,
      "exit_reason": "TP_HIT",
      "pnl_pips": 13.499999999999623,
      "pnl_dollars": 1.3499999999999623,
      "lots": 0.01,
      "r_multiple": 0.3374999999999903,
      "duration_minutes": 135,
      "signal_source": "MOMENTUM_BREAKOUT",
      "confidence": 99.0
    },
    {
      "id": 20,
      "direction": "SELL",
      "entry_time": "2026-01-05 22:10:00",
      "entry_price": 1.3541669246285242,
      "exit_time": "2026-01-06 10:00:00",
      "exit_price": 1.3531669246285243,
      "exit_reason": "TP_HIT",
      "pnl_pips": 9.999999999998899,
      "pnl_dollars": 0.9999999999998899,
      "lots": 0.01,
      "r_multiple": 0.24999999999997224,
      "duration_minutes": 710,
      "signal_source": "REVERSION_SNIPER",
      "confidence": 99.0
    },
    {
      "id": 27,
      "direction": "SELL",
      "entry_time": "2026-01-06 02:25:00",
      "entry_price": 1.3545750247624548,
      "exit_time": "2026-01-06 10:00:00",
      "exit_price": 1.353575024762455,
      "exit_reason": "TP_HIT",
      "pnl_pips": 9.999999999998899,
      "pnl_dollars": 0.9999999999998899,
      "lots": 0.01,
      "r_multiple": 0.24999999999997224,
      "duration_minutes": 455,
      "signal_source": "MOMENTUM_BREAKOUT",
      "confidence": 99.0
    },
    {
      "id": 28,
      "direction": "SELL",
      "entry_time": "2026-01-06 02:25:00",
      "entry_price": 1.3545666027798122,
      "exit_time": "2026-01-06 10:00:00",
      "exit_price": 1.3535666027798121,
      "exit_reason": "TP_HIT",
      "pnl_pips": 10.000000000001119,
      "pnl_dollars": 1.000000000000112,
      "lots": 0.01,
      "r_multiple": 0.25000000000002776,
      "duration_minutes": 455,
      "signal_source": "MOMENTUM_BREAKOUT",
      "confidence": 99.0
    },
    {
      "id": 42,
      "direction": "SELL",
      "entry_time": "2026-01-06 09:05:00",
      "entry_price": 1.3551037716478809,
      "exit_time": "2026-01-06 10:30:00",
      "exit_price": 1.3535037716478808,
      "exit_reason": "TP_HIT",
      "pnl_pips": 16.00000000000046,
      "pnl_dollars": 1.6000000000000458,
      "lots": 0.01,
      "r_multiple": 0.4000000000000111,
      "duration_minutes": 85,
      "signal_source": "REVERSION_SNIPER",
      "confidence": 99.0
    },
    {
      "id": 43,
      "direction": "SELL",
      "entry_time": "2026-01-06 09:05:00",
      "entry_price": 1.3551024415562034,
      "exit_time": "2026-01-06 10:30:00",
      "exit_price": 1.3535024415562034,
      "exit_reason": "TP_HIT",
      "pnl_pips": 16.00000000000046,
      "pnl_dollars": 1.6000000000000458,
      "lots": 0.01,
      "r_multiple": 0.4000000000000111,
      "duration_minutes": 85,
      "signal_source": "REVERSION_SNIPER",
      "confidence": 99.0
    },
    {
      "id": 44,
      "direction": "SELL",
      "entry_time": "2026-01-06 09:05:00",
      "entry_price": 1.3550972226104487,
      "exit_time": "2026-01-06 10:30:00",
      "exit_price": 1.3534972226104487,
      "exit_reason": "TP_HIT",
      "pnl_pips": 16.00000000000046,
      "pnl_dollars": 1.6000000000000458,
      "lots": 0.01,
      "r_multiple": 0.4000000000000111,
      "duration_minutes": 85,
      "signal_source": "REVERSION_SNIPER",
      "confidence": 99.0
    },
    {
      "id": 46,
      "direction": "SELL",
      "entry_time": "2026-01-06 09:05:00",
      "entry_price": 1.3550979509633487,
      "exit_time": "2026-01-06 10:30:00",
      "exit_price": 1.3534979509633487,
      "exit_reason": "TP_HIT",
      "pnl_pips": 16.00000000000046,
      "pnl_dollars": 1.6000000000000458,
      "lots": 0.01,
      "r_multiple": 0.4000000000000111,
      "duration_minutes": 85,
      "signal_source": "REVERSION_SNIPER",
      "confidence": 99.0
    },
    {
      "id": 45,
      "direction": "SELL",
      "entry_time": "2026-01-06 09:05:00",
      "entry_price": 1.3550771432813897,
      "exit_time": "2026-01-06 10:50:00",
      "exit_price": 1.3535771432813897,
      "exit_reason": "TP_HIT",
      "pnl_pips": 15.000000000000568,
      "pnl_dollars": 1.5000000000000568,
      "lots": 0.01,
      "r_multiple": 0.3750000000000139,
      "duration_minutes": 105,
      "signal_source": "REVERSION_SNIPER",
      "confidence": 99.0
    },
    {
      "id": 17,
      "direction": "SELL",
      "entry_time": "2026-01-05 22:10:00",
      "entry_price": 1.3541283169078444,
      "exit_time": "2026-01-06 11:05:00",
      "exit_price": 1.3531283169078443,
      "exit_reason": "TP_HIT",
      "pnl_pips": 10.000000000001119,
      "pnl_dollars": 1.000000000000112,
      "lots": 0.01,
      "r_multiple": 0.25000000000002776,
      "duration_minutes": 775,
      "signal_source": "REVERSION_SNIPER",
      "confidence": 99.0
    },
    {
      "id": 18,
      "direction": "SELL",
      "entry_time": "2026-01-05 22:10:00",
      "entry_price": 1.354151520262811,
      "exit_time": "2026-01-06 11:05:00",
      "exit_price": 1.353151520262811,
      "exit_reason": "TP_HIT",
      "pnl_pips": 9.999999999998899,
      "pnl_dollars": 0.9999999999998899,
      "lots": 0.01,
      "r_multiple": 0.24999999999997224,
      "duration_minutes": 775,
      "signal_source": "REVERSION_SNIPER",
      "confidence": 99.0
    },
    {
      "id": 19,
      "direction": "SELL",
      "entry_time": "2026-01-05 22:10:00",
      "entry_price": 1.35414096926038,
      "exit_time": "2026-01-06 11:05:00",
      "exit_price": 1.3531409692603802,
      "exit_reason": "TP_HIT",
      "pnl_pips": 9.999999999998899,
      "pnl_dollars": 0.9999999999998899,
      "lots": 0.01,
      "r_multiple": 0.24999999999997224,
      "duration_minutes": 775,
      "signal_source": "REVERSION_SNIPER",
      "confidence": 99.0
    },
    {
      "id": 21,
      "direction": "SELL",
      "entry_time": "2026-01-05 22:10:00",
      "entry_price": 1.3541216775590381,
      "exit_time": "2026-01-06 11:05:00",
      "exit_price": 1.353121677559038,
      "exit_reason": "TP_HIT",
      "pnl_pips": 10.000000000001119,
      "pnl_dollars": 1.000000000000112,
      "lots": 0.01,
      "r_multiple": 0.25000000000002776,
      "duration_minutes": 775,
      "signal_source": "REVERSION_SNIPER",
      "confidence": 99.0
    },
    {
      "id": 22,
      "direction": "SELL",
      "entry_time": "2026-01-05 22:40:00",
      "entry_price": 1.354104483397969,
      "exit_time": "2026-01-06 11:05:00",
      "exit_price": 1.3531044833979688,
      "exit_reason": "TP_HIT",
      "pnl_pips": 10.000000000001119,
      "pnl_dollars": 1.000000000000112,
      "lots": 0.01,
      "r_multiple": 0.25000000000002776,
      "duration_minutes": 745,
      "signal_source": "REVERSION_SNIPER",
      "confidence": 99.0
    },
    {
      "id": 23,
      "direction": "SELL",
      "entry_time": "2026-01-05 22:40:00",
      "entry_price": 1.3541164510692376,
      "exit_time": "2026-01-06 11:05:00",
      "exit_price": 1.3531164510692375,
      "exit_reason": "TP_HIT",
      "pnl_pips": 10.000000000001119,
      "pnl_dollars": 1.000000000000112,
      "lots": 0.01,
      "r_multiple": 0.25000000000002776,
      "duration_minutes": 745,
      "signal_source": "REVERSION_SNIPER",
      "confidence": 99.0
    },
    {
      "id": 24,
      "direction": "SELL",
      "entry_time": "2026-01-05 22:40:00",
      "entry_price": 1.3541100310942364,
      "exit_time": "2026-01-06 11:05:00",
      "exit_price": 1.3531100310942366,
      "exit_reason": "TP_HIT",
      "pnl_pips": 9.999999999998899,
      "pnl_dollars": 0.9999999999998899,
      "lots": 0.01,
      "r_multiple": 0.24999999999997224,
      "duration_minutes": 745,
      "signal_source": "REVERSION_SNIPER",
      "confidence": 99.0
    },
    {
      "id": 25,
      "direction": "SELL",
      "entry_time": "2026-01-05 22:40:00",
      "entry_price": 1.3541391467127024,
      "exit_time": "2026-01-06 11:05:00",
      "exit_price": 1.3531391467127025,
      "exit_reason": "TP_HIT",
      "pnl_pips": 9.999999999998899,
      "pnl_dollars": 0.9999999999998899,
      "lots": 0.01,
      "r_multiple": 0.24999999999997224,
      "duration_minutes": 745,
      "signal_source": "REVERSION_SNIPER",
      "confidence": 99.0
    },
    {
      "id": 26,
      "direction": "SELL",
      "entry_time": "2026-01-05 22:40:00",
      "entry_price": 1.35412762136077,
      "exit_time": "2026-01-06 11:05:00",
      "exit_price": 1.3531276213607701,
      "exit_reason": "TP_HIT",
      "pnl_pips": 9.999999999998899,
      "pnl_dollars": 0.9999999999998899,
      "lots": 0.01,
      "r_multiple": 0.24999999999997224,
      "duration_minutes": 745,
      "signal_source": "REVERSION_SNIPER",
      "confidence": 99.0
    },
    {
      "id": 3,
      "direction": "SELL",
      "entry_time": "2026-01-05 18:50:00",
      "entry_price": 1.3536495794635663,
      "exit_time": "2026-01-06 11:15:00",
      "exit_price": 1.3526495794635665,
      "exit_reason": "TP_HIT",
      "pnl_pips": 9.999999999998899,
      "pnl_dollars": 0.9999999999998899,
      "lots": 0.01,
      "r_multiple": 0.24999999999997224,
      "duration_minutes": 985,
      "signal_source": "MOMENTUM_BREAKOUT",
      "confidence": 99.0
    },
    {
      "id": 4,
      "direction": "SELL",
      "entry_time": "2026-01-05 18:50:00",
      "entry_price": 1.3536503656750527,
      "exit_time": "2026-01-06 11:15:00",
      "exit_price": 1.3526503656750526,
      "exit_reason": "TP_HIT",
      "pnl_pips": 10.000000000001119,
      "pnl_dollars": 1.000000000000112,
      "lots": 0.01,
      "r_multiple": 0.25000000000002776,
      "duration_minutes": 985,
      "signal_source": "MOMENTUM_BREAKOUT",
      "confidence": 99.0
    },
    {
      "id": 2,
      "direction": "SELL",
      "entry_time": "2026-01-05 18:25:00",
      "entry_price": 1.353010925834966,
      "exit_time": "2026-01-06 12:30:00",
      "exit_price": 1.352010925834966,
      "exit_reason": "TP_HIT",
      "pnl_pips": 10.000000000001119,
      "pnl_dollars": 1.000000000000112,
      "lots": 0.01,
      "r_multiple": 0.25000000000002776,
      "duration_minutes": 1085,
      "signal_source": "MOMENTUM_BREAKOUT",
      "confidence": 99.0
    },
    {
      "id": 1,
      "direction": "SELL",
      "entry_time": "2026-01-05 18:25:00",
      "entry_price": 1.352985162607541,
      "exit_time": "2026-01-06 12:40:00",
      "exit_price": 1.3519851626075412,
      "exit_reason": "TP_HIT",
      "pnl_pips": 9.999999999998899,
      "pnl_dollars": 0.9999999999998899,
      "lots": 0.01,
      "r_multiple": 0.24999999999997224,
      "duration_minutes": 1095,
      "signal_source": "MOMENTUM_BREAKOUT",
      "confidence": 99.0
    },
    {
      "id": 47,
      "direction": "SELL",
      "entry_time": "2026-01-06 18:25:00",
      "entry_price": 1.3506170841569625,
      "exit_time": "2026-01-07 07:45:00",
      "exit_price": 1.3496170841569626,
      "exit_reason": "TP_HIT",
      "pnl_pips": 9.999999999998899,
      "pnl_dollars": 0.9999999999998899,
      "lots": 0.01,
      "r_multiple": 0.24999999999997224,
      "duration_minutes": 800,
      "signal_source": "REVERSION_SNIPER",
      "confidence": 99.0
    },
    {
      "id": 48,
      "direction": "SELL",
      "entry_time": "2026-01-06 18:25:00",
      "entry_price": 1.3506113131999455,
      "exit_time": "2026-01-07 07:45:00",
      "exit_price": 1.3496113131999454,
      "exit_reason": "TP_HIT",
      "pnl_pips": 10.000000000001119,
      "pnl_dollars": 1.000000000000112,
      "lots": 0.01,
      "r_multiple": 0.25000000000002776,
      "duration_minutes": 800,
      "signal_source": "REVERSION_SNIPER",
      "confidence": 99.0
    },
    {
      "id": 49,
      "direction": "SELL",
      "entry_time": "2026-01-06 18:25:00",
      "entry_price": 1.350649633109465,
      "exit_time": "2026-01-07 07:45:00",
      "exit_price": 1.3496496331094652,
      "exit_reason": "TP_HIT",
      "pnl_pips": 9.999999999998899,
      "pnl_dollars": 0.9999999999998899,
      "lots": 0.01,
      "r_multiple": 0.24999999999997224,
      "duration_minutes": 800,
      "signal_source": "REVERSION_SNIPER",
      "confidence": 99.0
    },
    {
      "id": 50,
      "direction": "SELL",
      "entry_time": "2026-01-06 18:25:00",
      "entry_price": 1.3506228793820456,
      "exit_time": "2026-01-07 07:45:00",
      "exit_price": 1.3496228793820455,
      "exit_reason": "TP_HIT",
      "pnl_pips": 10.000000000001119,
      "pnl_dollars": 1.000000000000112,
      "lots": 0.01,
      "r_multiple": 0.25000000000002776,
      "duration_minutes": 800,
      "signal_source": "REVERSION_SNIPER",
      "confidence": 99.0
    },
    {
      "id": 51,
      "direction": "SELL",
      "entry_time": "2026-01-06 18:25:00",
      "entry_price": 1.350653594622949,
      "exit_time": "2026-01-07 07:45:00",
      "exit_price": 1.349653594622949,
      "exit_reason": "TP_HIT",
      "pnl_pips": 9.999999999998899,
      "pnl_dollars": 0.9999999999998899,
      "lots": 0.01,
      "r_multiple": 0.24999999999997224,
      "duration_minutes": 800,
      "signal_source": "REVERSION_SNIPER",
      "confidence": 99.0
    },
    {
      "id": 52,
      "direction": "SELL",
      "entry_time": "2026-01-06 22:25:00",
      "entry_price": 1.3498974178414755,
      "exit_time": "2026-01-07 08:00:00",
      "exit_price": 1.3488974178414757,
      "exit_reason": "TP_HIT",
      "pnl_pips": 9.999999999998899,
      "pnl_dollars": 0.9999999999998899,
      "lots": 0.01,
      "r_multiple": 0.24999999999997224,
      "duration_minutes": 575,
      "signal_source": "REVERSION_SNIPER",
      "confidence": 99.0
    },
    {
      "id": 53,
      "direction": "SELL",
      "entry_time": "2026-01-06 22:25:00",
      "entry_price": 1.3499414032766472,
      "exit_time": "2026-01-07 08:00:00",
      "exit_price": 1.3489414032766471,
      "exit_reason": "TP_HIT",
      "pnl_pips": 10.000000000001119,
      "pnl_dollars": 1.000000000000112,
      "lots": 0.01,
      "r_multiple": 0.25000000000002776,
      "duration_minutes": 575,
      "signal_source": "REVERSION_SNIPER",
      "confidence": 99.0
    },
    {
      "id": 54,
      "direction": "SELL",
      "entry_time": "2026-01-06 22:25:00",
      "entry_price": 1.349936265674947,
      "exit_time": "2026-01-07 08:00:00",
      "exit_price": 1.348936265674947,
      "exit_reason": "TP_HIT",
      "pnl_pips": 9.999999999998899,
      "pnl_dollars": 0.9999999999998899,
      "lots": 0.01,
      "r_multiple": 0.24999999999997224,
      "duration_minutes": 575,
      "signal_source": "REVERSION_SNIPER",
      "confidence": 99.0
    },
    {
      "id": 55,
      "direction": "SELL",
      "entry_time": "2026-01-06 22:25:00",
      "entry_price": 1.3499311943791399,
      "exit_time": "2026-01-07 08:00:00",
      "exit_price": 1.3489311943791398,
      "exit_reason": "TP_HIT",
      "pnl_pips": 10.000000000001119,
      "pnl_dollars": 1.000000000000112,
      "lots": 0.01,
      "r_multiple": 0.25000000000002776,
      "duration_minutes": 575,
      "signal_source": "REVERSION_SNIPER",
      "confidence": 99.0
    },
    {
      "id": 56,
      "direction": "SELL",
      "entry_time": "2026-01-06 22:25:00",
      "entry_price": 1.3499423770157148,
      "exit_time": "2026-01-07 08:00:00",
      "exit_price": 1.3489423770157147,
      "exit_reason": "TP_HIT",
      "pnl_pips": 10.000000000001119,
      "pnl_dollars": 1.000000000000112,
      "lots": 0.01,
      "r_multiple": 0.25000000000002776,
      "duration_minutes": 575,
      "signal_source": "REVERSION_SNIPER",
      "confidence": 99.0
    },
    {
      "id": 57,
      "direction": "SELL",
      "entry_time": "2026-01-07 11:30:00",
      "entry_price": 1.3499863835153294,
      "exit_time": "2026-01-07 13:10:00",
      "exit_price": 1.3484613835153294,
      "exit_reason": "TP_HIT",
      "pnl_pips": 15.249999999999986,
      "pnl_dollars": 1.5249999999999986,
      "lots": 0.01,
      "r_multiple": 0.3812499999999993,
      "duration_minutes": 100,
      "signal_source": "MOMENTUM_BREAKOUT",
      "confidence": 99.0
    },
    {
      "id": 58,
      "direction": "SELL",
      "entry_time": "2026-01-07 11:30:00",
      "entry_price": 1.349998499014656,
      "exit_time": "2026-01-07 13:10:00",
      "exit_price": 1.348473499014656,
      "exit_reason": "TP_HIT",
      "pnl_pips": 15.249999999999986,
      "pnl_dollars": 1.5249999999999986,
      "lots": 0.01,
      "r_multiple": 0.3812499999999993,
      "duration_minutes": 100,
      "signal_source": "MOMENTUM_BREAKOUT",
      "confidence": 99.0
    },
    {
      "id": 59,
      "direction": "SELL",
      "entry_time": "2026-01-07 12:00:00",
      "entry_price": 1.3501066248348406,
      "exit_time": "2026-01-07 13:10:00",
      "exit_price": 1.3484316248348405,
      "exit_reason": "TP_HIT",
      "pnl_pips": 16.75000000000093,
      "pnl_dollars": 1.675000000000093,
      "lots": 0.01,
      "r_multiple": 0.4187500000000229,
      "duration_minutes": 70,
      "signal_source": "MOMENTUM_BREAKOUT",
      "confidence": 99.0
    },
    {
      "id": 60,
      "direction": "SELL",
      "entry_time": "2026-01-07 12:00:00",
      "entry_price": 1.3501281175987991,
      "exit_time": "2026-01-07 13:10:00",
      "exit_price": 1.348453117598799,
      "exit_reason": "TP_HIT",
      "pnl_pips": 16.75000000000093,
      "pnl_dollars": 1.675000000000093,
      "lots": 0.01,
      "r_multiple": 0.4187500000000229,
      "duration_minutes": 70,
      "signal_source": "MOMENTUM_BREAKOUT",
      "confidence": 99.0
    },
    {
      "id": 61,
      "direction": "SELL",
      "entry_time": "2026-01-07 15:40:00",
      "entry_price": 1.3490357052780102,
      "exit_time": "2026-01-07 16:45:00",
      "exit_price": 1.3473357052780102,
      "exit_reason": "TP_HIT",
      "pnl_pips": 17.000000000000348,
      "pnl_dollars": 1.7000000000000348,
      "lots": 0.01,
      "r_multiple": 0.4250000000000083,
      "duration_minutes": 65,
      "signal_source": "CONSENSUS_VOTE",
      "confidence": 99.0
    },
    {
      "id": 63,
      "direction": "SELL",
      "entry_time": "2026-01-08 04:10:00",
      "entry_price": 1.3461471095468653,
      "exit_time": "2026-01-08 07:50:00",
      "exit_price": 1.3451471095468652,
      "exit_reason": "TP_HIT",
      "pnl_pips": 10.000000000001119,
      "pnl_dollars": 1.000000000000112,
      "lots": 0.01,
      "r_multiple": 0.25000000000002776,
      "duration_minutes": 220,
      "signal_source": "REVERSION_SNIPER",
      "confidence": 99.0
    },
    {
      "id": 64,
      "direction": "SELL",
      "entry_time": "2026-01-08 04:10:00",
      "entry_price": 1.3461489394207604,
      "exit_time": "2026-01-08 07:50:00",
      "exit_price": 1.3451489394207603,
      "exit_reason": "TP_HIT",
      "pnl_pips": 10.000000000001119,
      "pnl_dollars": 1.000000000000112,
      "lots": 0.01,
      "r_multiple": 0.25000000000002776,
      "duration_minutes": 220,
      "signal_source": "REVERSION_SNIPER",
      "confidence": 99.0
    },
    {
      "id": 65,
      "direction": "SELL",
      "entry_time": "2026-01-08 04:10:00",
      "entry_price": 1.3461532700955043,
      "exit_time": "2026-01-08 07:50:00",
      "exit_price": 1.3451532700955044,
      "exit_reason": "TP_HIT",
      "pnl_pips": 9.999999999998899,
      "pnl_dollars": 0.9999999999998899,
      "lots": 0.01,
      "r_multiple": 0.24999999999997224,
      "duration_minutes": 220,
      "signal_source": "REVERSION_SNIPER",
      "confidence": 99.0
    },
    {
      "id": 66,
      "direction": "SELL",
      "entry_time": "2026-01-08 04:10:00",
      "entry_price": 1.3461747484467492,
      "exit_time": "2026-01-08 07:50:00",
      "exit_price": 1.3451747484467491,
      "exit_reason": "TP_HIT",
      "pnl_pips": 10.000000000001119,
      "pnl_dollars": 1.000000000000112,
      "lots": 0.01,
      "r_multiple": 0.25000000000002776,
      "duration_minutes": 220,
      "signal_source": "REVERSION_SNIPER",
      "confidence": 99.0
    },
    {
      "id": 67,
      "direction": "SELL",
      "entry_time": "2026-01-08 04:10:00",
      "entry_price": 1.3461575087237305,
      "exit_time": "2026-01-08 07:50:00",
      "exit_price": 1.3451575087237306,
      "exit_reason": "TP_HIT",
      "pnl_pips": 9.999999999998899,
      "pnl_dollars": 0.9999999999998899,
      "lots": 0.01,
      "r_multiple": 0.24999999999997224,
      "duration_minutes": 220,
      "signal_source": "REVERSION_SNIPER",
      "confidence": 99.0
    },
    {
      "id": 62,
      "direction": "SELL",
      "entry_time": "2026-01-08 00:40:00",
      "entry_price": 1.345838113297236,
      "exit_time": "2026-01-08 07:55:00",
      "exit_price": 1.3448381132972358,
      "exit_reason": "TP_HIT",
      "pnl_pips": 10.000000000001119,
      "pnl_dollars": 1.000000000000112,
      "lots": 0.01,
      "r_multiple": 0.25000000000002776,
      "duration_minutes": 435,
      "signal_source": "CONSENSUS_VOTE",
      "confidence": 99.0
    },
    {
      "id": 68,
      "direction": "SELL",
      "entry_time": "2026-01-08 04:35:00",
      "entry_price": 1.3460920846530442,
      "exit_time": "2026-01-08 07:55:00",
      "exit_price": 1.3450670846530441,
      "exit_reason": "TP_HIT",
      "pnl_pips": 10.250000000000536,
      "pnl_dollars": 1.0250000000000536,
      "lots": 0.01,
      "r_multiple": 0.2562500000000132,
      "duration_minutes": 200,
      "signal_source": "REVERSION_SNIPER",
      "confidence": 99.0
    },
    {
      "id": 69,
      "direction": "SELL",
      "entry_time": "2026-01-08 04:35:00",
      "entry_price": 1.3460957823027515,
      "exit_time": "2026-01-08 07:55:00",
      "exit_price": 1.3450707823027515,
      "exit_reason": "TP_HIT",
      "pnl_pips": 10.250000000000536,
      "pnl_dollars": 1.0250000000000536,
      "lots": 0.01,
      "r_multiple": 0.2562500000000132,
      "duration_minutes": 200,
      "signal_source": "REVERSION_SNIPER",
      "confidence": 99.0
    },
    {
      "id": 70,
      "direction": "SELL",
      "entry_time": "2026-01-08 04:35:00",
      "entry_price": 1.3461009469498315,
      "exit_time": "2026-01-08 07:55:00",
      "exit_price": 1.3450759469498315,
      "exit_reason": "TP_HIT",
      "pnl_pips": 10.250000000000536,
      "pnl_dollars": 1.0250000000000536,
      "lots": 0.01,
      "r_multiple": 0.2562500000000132,
      "duration_minutes": 200,
      "signal_source": "REVERSION_SNIPER",
      "confidence": 99.0
    },
    {
      "id": 71,
      "direction": "SELL",
      "entry_time": "2026-01-08 04:35:00",
      "entry_price": 1.3460896186895739,
      "exit_time": "2026-01-08 07:55:00",
      "exit_price": 1.3450646186895738,
      "exit_reason": "TP_HIT",
      "pnl_pips": 10.250000000000536,
      "pnl_dollars": 1.0250000000000536,
      "lots": 0.01,
      "r_multiple": 0.2562500000000132,
      "duration_minutes": 200,
      "signal_source": "REVERSION_SNIPER",
      "confidence": 99.0
    },
    {
      "id": 72,
      "direction": "SELL",
      "entry_time": "2026-01-08 04:35:00",
      "entry_price": 1.3461214433485538,
      "exit_time": "2026-01-08 07:55:00",
      "exit_price": 1.3450964433485537,
      "exit_reason": "TP_HIT",
      "pnl_pips": 10.250000000000536,
      "pnl_dollars": 1.0250000000000536,
      "lots": 0.01,
      "r_multiple": 0.2562500000000132,
      "duration_minutes": 200,
      "signal_source": "REVERSION_SNIPER",
      "confidence": 99.0
    },
    {
      "id": 73,
      "direction": "SELL",
      "entry_time": "2026-01-08 12:20:00",
      "entry_price": 1.3443169711899425,
      "exit_time": "2026-01-08 13:45:00",
      "exit_price": 1.3427169711899425,
      "exit_reason": "TP_HIT",
      "pnl_pips": 16.00000000000046,
      "pnl_dollars": 12.800000000000367,
      "lots": 0.08,
      "r_multiple": 0.4000000000000111,
      "duration_minutes": 85,
      "signal_source": "REVERSION_SNIPER",
      "confidence": 99.0
    },
    {
      "id": 74,
      "direction": "SELL",
      "entry_time": "2026-01-08 12:20:00",
      "entry_price": 1.3443461611090868,
      "exit_time": "2026-01-08 13:45:00",
      "exit_price": 1.3427461611090867,
      "exit_reason": "TP_HIT",
      "pnl_pips": 16.00000000000046,
      "pnl_dollars": 12.800000000000367,
      "lots": 0.08,
      "r_multiple": 0.4000000000000111,
      "duration_minutes": 85,
      "signal_source": "REVERSION_SNIPER",
      "confidence": 99.0
    },
    {
      "id": 75,
      "direction": "SELL",
      "entry_time": "2026-01-08 12:20:00",
      "entry_price": 1.3443178546605485,
      "exit_time": "2026-01-08 13:45:00",
      "exit_price": 1.3427178546605485,
      "exit_reason": "TP_HIT",
      "pnl_pips": 16.00000000000046,
      "pnl_dollars": 12.800000000000367,
      "lots": 0.08,
      "r_multiple": 0.4000000000000111,
      "duration_minutes": 85,
      "signal_source": "REVERSION_SNIPER",
      "confidence": 99.0
    },
    {
      "id": 76,
      "direction": "SELL",
      "entry_time": "2026-01-08 12:20:00",
      "entry_price": 1.3443457722349745,
      "exit_time": "2026-01-08 13:45:00",
      "exit_price": 1.3427457722349745,
      "exit_reason": "TP_HIT",
      "pnl_pips": 16.00000000000046,
      "pnl_dollars": 12.800000000000367,
      "lots": 0.08,
      "r_multiple": 0.4000000000000111,
      "duration_minutes": 85,
      "signal_source": "REVERSION_SNIPER",
      "confidence": 99.0
    },
    {
      "id": 77,
      "direction": "SELL",
      "entry_time": "2026-01-08 12:20:00",
      "entry_price": 1.3443266492316597,
      "exit_time": "2026-01-08 13:45:00",
      "exit_price": 1.3427266492316596,
      "exit_reason": "TP_HIT",
      "pnl_pips": 16.00000000000046,
      "pnl_dollars": 12.800000000000367,
      "lots": 0.08,
      "r_multiple": 0.4000000000000111,
      "duration_minutes": 85,
      "signal_source": "REVERSION_SNIPER",
      "confidence": 99.0
    },
    {
      "id": 78,
      "direction": "SELL",
      "entry_time": "2026-01-09 05:15:00",
      "entry_price": 1.343570378543127,
      "exit_time": "2026-01-09 07:10:00",
      "exit_price": 1.342120378543127,
      "exit_reason": "TP_HIT",
      "pnl_pips": 14.499999999999513,
      "pnl_dollars": 18.84999999999937,
      "lots": 0.13,
      "r_multiple": 0.3624999999999875,
      "duration_minutes": 115,
      "signal_source": "MOMENTUM_BREAKOUT",
      "confidence": 99.0
    },
    {
      "id": 79,
      "direction": "SELL",
      "entry_time": "2026-01-09 05:15:00",
      "entry_price": 1.3435766332222494,
      "exit_time": "2026-01-09 07:10:00",
      "exit_price": 1.3421266332222495,
      "exit_reason": "TP_HIT",
      "pnl_pips": 14.499999999999513,
      "pnl_dollars": 18.84999999999937,
      "lots": 0.13,
      "r_multiple": 0.3624999999999875,
      "duration_minutes": 115,
      "signal_source": "MOMENTUM_BREAKOUT",
      "confidence": 99.0
    },
    {
      "id": 80,
      "direction": "SELL",
      "entry_time": "2026-01-09 08:10:00",
      "entry_price": 1.342520669254674,
      "exit_time": "2026-01-09 09:45:00",
      "exit_price": 1.3409706692546741,
      "exit_reason": "TP_HIT",
      "pnl_pips": 15.499999999999403,
      "pnl_dollars": 24.799999999999045,
      "lots": 0.16,
      "r_multiple": 0.38749999999998475,
      "duration_minutes": 95,
      "signal_source": "CONSENSUS_VOTE",
      "confidence": 99.0
    },
    {
      "id": 81,
      "direction": "SELL",
      "entry_time": "2026-01-09 13:55:00",
      "entry_price": 1.343340798642958,
      "exit_time": "2026-01-09 14:40:00",
      "exit_price": 1.341340798642958,
      "exit_reason": "TP_HIT",
      "pnl_pips": 20.000000000000018,
      "pnl_dollars": 36.00000000000003,
      "lots": 0.18,
      "r_multiple": 0.5,
      "duration_minutes": 45,
      "signal_source": "REVERSION_SNIPER",
      "confidence": 99.0
    },
    {
      "id": 82,
      "direction": "SELL",
      "entry_time": "2026-01-09 13:55:00",
      "entry_price": 1.3433754120088344,
      "exit_time": "2026-01-09 14:40:00",
      "exit_price": 1.3413754120088344,
      "exit_reason": "TP_HIT",
      "pnl_pips": 20.000000000000018,
      "pnl_dollars": 36.00000000000003,
      "lots": 0.18,
      "r_multiple": 0.5,
      "duration_minutes": 45,
      "signal_source": "REVERSION_SNIPER",
      "confidence": 99.0
    },
    {
      "id": 83,
      "direction": "SELL",
      "entry_time": "2026-01-09 13:55:00",
      "entry_price": 1.3433554752078505,
      "exit_time": "2026-01-09 14:40:00",
      "exit_price": 1.3413554752078505,
      "exit_reason": "TP_HIT",
      "pnl_pips": 20.000000000000018,
      "pnl_dollars": 36.00000000000003,
      "lots": 0.18,
      "r_multiple": 0.5,
      "duration_minutes": 45,
      "signal_source": "REVERSION_SNIPER",
      "confidence": 99.0
    },
    {
      "id": 84,
      "direction": "SELL",
      "entry_time": "2026-01-09 13:55:00",
      "entry_price": 1.3433808158900193,
      "exit_time": "2026-01-09 14:40:00",
      "exit_price": 1.3413808158900193,
      "exit_reason": "TP_HIT",
      "pnl_pips": 20.000000000000018,
      "pnl_dollars": 36.00000000000003,
      "lots": 0.18,
      "r_multiple": 0.5,
      "duration_minutes": 45,
      "signal_source": "REVERSION_SNIPER",
      "confidence": 99.0
    },
    {
      "id": 85,
      "direction": "SELL",
      "entry_time": "2026-01-09 13:55:00",
      "entry_price": 1.3433450301933498,
      "exit_time": "2026-01-09 14:40:00",
      "exit_price": 1.3413450301933498,
      "exit_reason": "TP_HIT",
      "pnl_pips": 20.000000000000018,
      "pnl_dollars": 36.00000000000003,
      "lots": 0.18,
      "r_multiple": 0.5,
      "duration_minutes": 45,
      "signal_source": "REVERSION_SNIPER",
      "confidence": 99.0
    },
    {
      "id": 87,
      "direction": "SELL",
      "entry_time": "2026-01-12 01:30:00",
      "entry_price": 1.343309177357565,
      "exit_time": "2026-01-12 04:25:00",
      "exit_price": 1.342159177357565,
      "exit_reason": "TP_HIT",
      "pnl_pips": 11.499999999999844,
      "pnl_dollars": 35.649999999999515,
      "lots": 0.31,
      "r_multiple": 0.2874999999999958,
      "duration_minutes": 175,
      "signal_source": "MOMENTUM_BREAKOUT",
      "confidence": 99.0
    },
    {
      "id": 86,
      "direction": "SELL",
      "entry_time": "2026-01-12 01:30:00",
      "entry_price": 1.34328314136099,
      "exit_time": "2026-01-12 04:30:00",
      "exit_price": 1.34215814136099,
      "exit_reason": "TP_HIT",
      "pnl_pips": 11.250000000000426,
      "pnl_dollars": 34.87500000000132,
      "lots": 0.31,
      "r_multiple": 0.2812500000000104,
      "duration_minutes": 180,
      "signal_source": "MOMENTUM_BREAKOUT",
      "confidence": 99.0
    },
    {
      "id": 88,
      "direction": "SELL",
      "entry_time": "2026-01-12 01:55:00",
      "entry_price": 1.3428965150908403,
      "exit_time": "2026-01-12 05:30:00",
      "exit_price": 1.3435261249542236,
      "exit_reason": "VSL_HIT",
      "pnl_pips": -6.296098633833402,
      "pnl_dollars": -19.517905764883547,
      "lots": 0.31,
      "r_multiple": -0.15740246584583492,
      "duration_minutes": 215,
      "signal_source": "MOMENTUM_BREAKOUT",
      "confidence": 99.0
    },
    {
      "id": 89,
      "direction": "SELL",
      "entry_time": "2026-01-12 01:55:00",
      "entry_price": 1.3428748859359843,
      "exit_time": "2026-01-12 05:30:00",
      "exit_price": 1.3435261249542236,
      "exit_reason": "VSL_HIT",
      "pnl_pips": -6.512390182393801,
      "pnl_dollars": -20.188409565420784,
      "lots": 0.31,
      "r_multiple": -0.1628097545598449,
      "duration_minutes": 215,
      "signal_source": "MOMENTUM_BREAKOUT",
      "confidence": 99.0
    },
    {
      "id": 90,
      "direction": "SELL",
      "entry_time": "2026-01-12 02:25:00",
      "entry_price": 1.34264340720533,
      "exit_time": "2026-01-12 05:30:00",
      "exit_price": 1.3435261249542236,
      "exit_reason": "VSL_HIT",
      "pnl_pips": -8.827177488937021,
      "pnl_dollars": -27.364250215704768,
      "lots": 0.31,
      "r_multiple": -0.22067943722342534,
      "duration_minutes": 185,
      "signal_source": "REVERSION_SNIPER",
      "confidence": 99.0
    },
    {
      "id": 91,
      "direction": "SELL",
      "entry_time": "2026-01-12 02:25:00",
      "entry_price": 1.342629167322701,
      "exit_time": "2026-01-12 05:30:00",
      "exit_price": 1.3435261249542236,
      "exit_reason": "VSL_HIT",
      "pnl_pips": -8.969576315225325,
      "pnl_dollars": -27.805686577198507,
      "lots": 0.31,
      "r_multiple": -0.22423940788063293,
      "duration_minutes": 185,
      "signal_source": "REVERSION_SNIPER",
      "confidence": 99.0
    },
    {
      "id": 92,
      "direction": "SELL",
      "entry_time": "2026-01-12 02:25:00",
      "entry_price": 1.3426411885201845,
      "exit_time": "2026-01-12 05:30:00",
      "exit_price": 1.3435261249542236,
      "exit_reason": "VSL_HIT",
      "pnl_pips": -8.849364340390853,
      "pnl_dollars": -27.433029455211646,
      "lots": 0.31,
      "r_multiple": -0.22123410850977113,
      "duration_minutes": 185,
      "signal_source": "REVERSION_SNIPER",
      "confidence": 99.0
    },
    {
      "id": 93,
      "direction": "SELL",
      "entry_time": "2026-01-12 02:25:00",
      "entry_price": 1.3426438425419818,
      "exit_time": "2026-01-12 05:30:00",
      "exit_price": 1.3435261249542236,
      "exit_reason": "VSL_HIT",
      "pnl_pips": -8.822824122418638,
      "pnl_dollars": -27.350754779497777,
      "lots": 0.31,
      "r_multiple": -0.22057060306046575,
      "duration_minutes": 185,
      "signal_source": "REVERSION_SNIPER",
      "confidence": 99.0
    },
    {
      "id": 94,
      "direction": "SELL",
      "entry_time": "2026-01-12 02:25:00",
      "entry_price": 1.3426437687017236,
      "exit_time": "2026-01-12 05:30:00",
      "exit_price": 1.3435261249542236,
      "exit_reason": "VSL_HIT",
      "pnl_pips": -8.82356252499994,
      "pnl_dollars": -27.353043827499814,
      "lots": 0.31,
      "r_multiple": -0.2205890631249983,
      "duration_minutes": 185,
      "signal_source": "REVERSION_SNIPER",
      "confidence": 99.0
    },
    {
      "id": 95,
      "direction": "SELL",
      "entry_time": "2026-01-12 02:50:00",
      "entry_price": 1.3427066184785823,
      "exit_time": "2026-01-12 05:30:00",
      "exit_price": 1.3435261249542236,
      "exit_reason": "VSL_HIT",
      "pnl_pips": -8.195064756413295,
      "pnl_dollars": -25.404700744881215,
      "lots": 0.31,
      "r_multiple": -0.20487661891033218,
      "duration_minutes": 160,
      "signal_source": "REVERSION_SNIPER",
      "confidence": 99.0
    },
    {
      "id": 96,
      "direction": "SELL",
      "entry_time": "2026-01-12 02:50:00",
      "entry_price": 1.3426788797334894,
      "exit_time": "2026-01-12 05:30:00",
      "exit_price": 1.3435261249542236,
      "exit_reason": "VSL_HIT",
      "pnl_pips": -8.472452207342052,
      "pnl_dollars": -26.26460184276036,
      "lots": 0.31,
      "r_multiple": -0.2118113051835511,
      "duration_minutes": 160,
      "signal_source": "REVERSION_SNIPER",
      "confidence": 99.0
    },
    {
      "id": 97,
      "direction": "SELL",
      "entry_time": "2026-01-12 02:50:00",
      "entry_price": 1.3426721212069312,
      "exit_time": "2026-01-12 05:30:00",
      "exit_price": 1.3435261249542236,
      "exit_reason": "VSL_HIT",
      "pnl_pips": -8.540037472923867,
      "pnl_dollars": -26.47411616606399,
      "lots": 0.31,
      "r_multiple": -0.21350093682309648,
      "duration_minutes": 160,
      "signal_source": "REVERSION_SNIPER",
      "confidence": 99.0
    },
    {
      "id": 98,
      "direction": "SELL",
      "entry_time": "2026-01-12 02:50:00",
      "entry_price": 1.342694349425569,
      "exit_time": "2026-01-12 05:30:00",
      "exit_price": 1.3435261249542236,
      "exit_reason": "VSL_HIT",
      "pnl_pips": -8.317755286546547,
      "pnl_dollars": -25.785041388294296,
      "lots": 0.31,
      "r_multiple": -0.20794388216366347,
      "duration_minutes": 160,
      "signal_source": "REVERSION_SNIPER",
      "confidence": 99.0
    },
    {
      "id": 99,
      "direction": "SELL",
      "entry_time": "2026-01-12 02:50:00",
      "entry_price": 1.3426864815281268,
      "exit_time": "2026-01-12 05:30:00",
      "exit_price": 1.3435261249542236,
      "exit_reason": "VSL_HIT",
      "pnl_pips": -8.39643426096881,
      "pnl_dollars": -26.028946209003312,
      "lots": 0.31,
      "r_multiple": -0.20991085652422006,
      "duration_minutes": 160,
      "signal_source": "REVERSION_SNIPER",
      "confidence": 99.0
    },
    {
      "id": 100,
      "direction": "SELL",
      "entry_time": "2026-01-12 03:20:00",
      "entry_price": 1.342682400080024,
      "exit_time": "2026-01-12 05:30:00",
      "exit_price": 1.3435261249542236,
      "exit_reason": "VSL_HIT",
      "pnl_pips": -8.437248741997028,
      "pnl_dollars": -26.155471100190788,
      "lots": 0.31,
      "r_multiple": -0.2109312185499255,
      "duration_minutes": 130,
      "signal_source": "CONSENSUS_VOTE",
      "confidence": 99.0
    }
  ]
}